swagcli/__init__.py
swagcli/auth.py
swagcli/cache.py
swagcli/cli.py
swagcli/client.py
swagcli/commands.py
swagcli/commandstore.py
swagcli/config.py
swagcli/models.py
swagcli/plugins/__init__.py
swagcli/plugins/example.py
swagcli/plugins/file_handler.py
swagcli/plugins/metrics.py
swagcli/plugins/rate_limiter.py
swagcli/plugins/validator.py
swagcli-0.2.0.dist-info/METADATA
swagcli-0.2.0.dist-info/WHEEL
swagcli-0.2.0.dist-info/RECORD
