Metadata-Version: 2.4
Name: swagcli
Version: 0.2.0
Summary: Make easy command line interfaces using swagger config
Author-email: Justin Thomas <git@imthor.in>
License-Expression: MIT
Requires-Python: >=3.8
Requires-Dist: aiofiles>=23.0.0
Requires-Dist: aiohttp>=3.8.0
Requires-Dist: click>=8.0.0
Requires-Dist: diskcache>=5.6.0
Requires-Dist: jsonschema>=4.20.0
Requires-Dist: prompt-toolkit>=3.0.0
Requires-Dist: pydantic>=2.0.0
Requires-Dist: pyjwt>=2.8.0
Requires-Dist: python-dotenv>=1.0.0
Requires-Dist: python-multipart>=0.0.6
Requires-Dist: pyyaml>=6.0.0
Requires-Dist: requests>=2.31.0
Requires-Dist: rich>=13.0.0
Requires-Dist: typer>=0.9.0
Provides-Extra: dev
Requires-Dist: black>=23.0.0; extra == 'dev'
Requires-Dist: isort>=5.0.0; extra == 'dev'
Requires-Dist: mypy>=1.0.0; extra == 'dev'
Requires-Dist: pytest-asyncio>=0.21.0; extra == 'dev'
Requires-Dist: pytest-cov>=4.1.0; extra == 'dev'
Requires-Dist: pytest>=7.0.0; extra == 'dev'
Requires-Dist: ruff>=0.1.0; extra == 'dev'
